{"about_buy.md":"DONz9LZa","about_community.md":"BTXslkv3","about_dev.md":"CQid8e5z","about_donate.md":"DXbYf2EI","guide_about.md":"C_wiBdvn","guide_basic_authorization.md":"BsdbyUkT","guide_basic_autoapi.md":"C4redYxp","guide_basic_batch.md":"B0iHQh90","guide_basic_cache.md":"BysC-hn5","guide_basic_cap.md":"C0F67LSt","guide_basic_cli.md":"CYOi-hDL","guide_basic_cors.md":"FBvmW8Wc","guide_basic_csharpclientproxy.md":"C_5bAUrh","guide_basic_dapper.md":"BoykzYHB","guide_basic_datafiltering.md":"B9HCoaKN","guide_basic_dataseeding.md":"BdvcQreF","guide_basic_distributed-locking.md":"C7BzRgKj","guide_basic_elastic.md":"D9LI7ydC","guide_basic_entity-extensions.md":"BmYbg3Te","guide_basic_event-bus-local.md":"BBkwdACk","guide_basic_export.md":"BZa57oy1","guide_basic_freesql.md":"BbFUwkJC","guide_basic_github-token.md":"Dc2hV0l5","guide_basic_job.md":"yAHt-keB","guide_basic_log.md":"DWuJGKSw","guide_basic_login.md":"BTeot7Ek","guide_basic_result.md":"BoXj48yv","guide_basic_setting.md":"DeoWc9Sz","guide_basic_switchdatatabse.md":"zl1hdrHL","guide_basic_tenant.md":"B3dtfTjx","guide_basic_thridpartylogin.md":"DfQPud5m","guide_basic_twofactor.md":"CIuJ9-oL","guide_basic_web-apiclient-core.md":"C1fmjdCI","guide_deploy_docker.md":"DLBQZ0iK","guide_modules_basic.md":"DgJ9Iaza","guide_modules_code.md":"BYlQcgRW","guide_modules_dic.md":"BZgA-6Fa","guide_modules_language.md":"2WcHfprJ","guide_modules_notification.md":"70t1iOQc","guide_quick-ddd.md":"Dc6TChCo","guide_quick-dev.md":"BNjIOmOc","guide_quick-start.md":"BN1GnrGy","guide_update_8.x-9.0.3.md":"DfgQBYL3","guide_wyh.md":"WZQTgN7V","index.md":"DshqK7_P","nav_index.md":"Cedg_4BU","vben5_check-updates.md":"BLdkw8Re","vben5_deploy.md":"fN12r7ri","vben5_faq.md":"wOtZJjb1","vben5_iis.md":"iMBV9Ptd","vben5_pub.md":"BZpcP94n","vben5_quick-start.md":"CTMVmP7C","vben5_route.md":"CD0LwAPd","vben5_thin.md":"C9BEueyK","vben5_update.md":"CKqRDnls"}
